solnir/__init__.py
solnir/core.py
solnir-0.1.8.dist-info/METADATA
solnir-0.1.8.dist-info/WHEEL
solnir-0.1.8.dist-info/top_level.txt
solnir-0.1.8.dist-info/RECORD
