Metadata-Version: 2.1
Name: solnir
Version: 0.1.8
Requires-Dist: pika
